odoo/addons/sale_product_identification/README.rst
odoo/addons/sale_product_identification/__init__.py
odoo/addons/sale_product_identification/__manifest__.py
odoo/addons/sale_product_identification/i18n/es.po
odoo/addons/sale_product_identification/i18n/it.po
odoo/addons/sale_product_identification/i18n/sale_product_identification.pot
odoo/addons/sale_product_identification/models/__init__.py
odoo/addons/sale_product_identification/models/product_template.py
odoo/addons/sale_product_identification/models/product_template_id_category.py
odoo/addons/sale_product_identification/models/res_partner_id_number.py
odoo/addons/sale_product_identification/models/sale_order.py
odoo/addons/sale_product_identification/readme/CONTRIBUTORS.md
odoo/addons/sale_product_identification/readme/DESCRIPTION.md
odoo/addons/sale_product_identification/readme/USAGE.md
odoo/addons/sale_product_identification/security/ir.model.access.csv
odoo/addons/sale_product_identification/static/description/icon.png
odoo/addons/sale_product_identification/static/description/index.html
odoo/addons/sale_product_identification/static/img/readme/ADD_IDENTIFICATION.png
odoo/addons/sale_product_identification/static/img/readme/CATEGORIES_REQUIRED.png
odoo/addons/sale_product_identification/static/img/readme/CONFIRM_IDENTIFICATION.png
odoo/addons/sale_product_identification/tests/__init__.py
odoo/addons/sale_product_identification/tests/sale_product_identification_common.py
odoo/addons/sale_product_identification/tests/test_sale_product_identification.py
odoo/addons/sale_product_identification/views/product_template_views.xml
odoo/addons/sale_product_identification/wizards/__init__.py
odoo/addons/sale_product_identification/wizards/wizard_confirm_identification.py
odoo/addons/sale_product_identification/wizards/wizard_confirm_identification.xml
odoo_addon_sale_product_identification-18.0.1.0.0.4.dist-info/METADATA
odoo_addon_sale_product_identification-18.0.1.0.0.4.dist-info/WHEEL
odoo_addon_sale_product_identification-18.0.1.0.0.4.dist-info/top_level.txt
odoo_addon_sale_product_identification-18.0.1.0.0.4.dist-info/RECORD
